<?xml version="1.0" encoding="UTF-8"?><database>
    <element db_object_id="3279aa7e83f61610f7969f65eeaad384" extends="task" label="Suggestion" max_length="40" name="x_1305322_raas_suggestion" type="collection">
        <element label="Media" max_length="32" name="media" reference="x_1305322_raas_media" type="reference"/>
        <element choice="1" label="Type" max_length="40" name="type" type="choice">
            <choice>
                <element inactive_on_update="false" label="Series" sequence="2" value="series"/>
                <element inactive="true" inactive_on_update="true" label="Episode" sequence="0" value="episode"/>
                <element inactive_on_update="false" label="Movie" sequence="1" value="movie"/>
            </choice>
        </element>
        <element label="Reproval Reason" max_length="4000" name="reproval_reason" type="string"/>
        <element label="Release Year" max_length="40" name="release_year" type="string"/>
        <element label="Title" max_length="250" name="title" type="string"/>
    </element>
</database>
